{
  "longName": "Carnarvon Energy Limited",
  "sector": "Energy",
  "industry": "Oil & Gas E&P",
  "country": "Australia",
  "currency": "AUD",
  "marketCap": 205744992,
  "enterpriseValue": 109916000,
  "fullTimeEmployees": 6,
  "longBusinessSummary": "Carnarvon Energy Limited engages in the exploration, development, and production of oil and gas properties in Australia. It owns various interests in the Dorado, Pavo, Roc, Phoenix, and Phoenix South project located in the Bedout Sub-basin permits of Western Australia. The company engages in carbon initiatives and new energy business. The company was incorporated in 1983 and is based in West Perth, Australia.",
  "website": "https://carnarvon.com.au",
  "exchange": "ASX",
  "trailingPE": null,
  "forwardPE": -34.12463,
  "priceToBook": 0.7718121,
  "dividendYield": null,
  "payoutRatio": 0.0,
  "beta": 0.679,
  "52WeekChange": 0.09523809,
  "totalRevenue": -2110000,
  "revenueGrowth": -0.737,
  "grossMargins": 0.0,
  "operatingMargins": -0.76689005,
  "profitMargins": 0.0,
  "returnOnAssets": -0.011469999,
  "returnOnEquity": -0.018609999,
  "totalDebt": 292000,
  "totalCash": 98296000,
  "debtToEquity": 0.108,
  "currentRatio": 136.782,
  "quickRatio": 136.079,
  "freeCashflow": -3393500,
  "operatingCashflow": 3429000,
  "ticker": "CVN.AX",
  "fetched_at": "2026-06-10T02:40:04.101507"
}